LICENSE
MANIFEST.in
README.rst
setup.cfg
setup.py
versioneer.py
pyatran/__init__.py
pyatran/_version.py
pyatran.egg-info/PKG-INFO
pyatran.egg-info/SOURCES.txt
pyatran.egg-info/dependency_links.txt
pyatran.egg-info/requires.txt
pyatran.egg-info/top_level.txt
pyatran/input/__init__.py
pyatran/input/input.py
pyatran/output/__init__.py
pyatran/output/output.py
pyatran/output/read_inp_pars.py
pyatran/output/read_sciatran.py
pyatran/params/__init__.py
pyatran/params/params.py
pyatran/runtime/__init__.py
pyatran/runtime/runtime.py
pyatran/util/__init__.py
pyatran/util/util.py